metricFTW/__init__.py
metricFTW/converter.py
noWeirdNumbersPls/__init__.py
noWeirdNumbersPls/format_number.py
quanticTime/__init__.py
quanticTime/core.py
noweirdutils-0.2.0.dist-info/entry_points.txt
noweirdutils-0.2.0.dist-info/LICENSE
noweirdutils-0.2.0.dist-info/METADATA
noweirdutils-0.2.0.dist-info/WHEEL
noweirdutils-0.2.0.dist-info/RECORD
