Metadata-Version: 2.3
Name: noWeirdUtils
Version: 0.2.0
Summary: Lightweight, fun named utilities for number formatting, unit conversions and unix time handling.
Author: Santiago Matta
Author-email: santiagomatta@outlook.cl
Requires-Python: >=3.9
Classifier: Development Status :: 4 - Beta
Classifier: Intended Audience :: Developers
Classifier: License :: OSI Approved :: MIT License
Classifier: Operating System :: OS Independent
Classifier: Programming Language :: Python :: 3
Classifier: Programming Language :: Python :: 3.9
Classifier: Programming Language :: Python :: 3.10
Classifier: Programming Language :: Python :: 3.11
Classifier: Programming Language :: Python :: 3.12
Classifier: Programming Language :: Python :: 3.13
Classifier: Topic :: Software Development :: Libraries :: Python Modules
Provides-Extra: fastmetric
Provides-Extra: timezone
Requires-Dist: numpy (>=1.25,<2.0) ; extra == "fastmetric"
Requires-Dist: pytz (>=2025.2,<2026.0) ; extra == "timezone"
Project-URL: homepage, https://github.com/santiago897/no_weird_project
